aldryn_forms/__init__.py
aldryn_forms/action_backends.py
aldryn_forms/action_backends_base.py
aldryn_forms/cms_apps.py
aldryn_forms/cms_plugins.py
aldryn_forms/compat.py
aldryn_forms/forms.py
aldryn_forms/helpers.py
aldryn_forms/models.py
aldryn_forms/signals.py
aldryn_forms/urls.py
aldryn_forms/utils.py
aldryn_forms/validators.py
aldryn_forms/views.py
aldryn_forms/admin/__init__.py
aldryn_forms/admin/base.py
aldryn_forms/admin/exporter.py
aldryn_forms/admin/forms.py
aldryn_forms/admin/views.py
aldryn_forms/contrib/__init__.py
aldryn_forms/contrib/email_notifications/__init__.py
aldryn_forms/contrib/email_notifications/cms_plugins.py
aldryn_forms/contrib/email_notifications/helpers.py
aldryn_forms/contrib/email_notifications/models.py
aldryn_forms/contrib/email_notifications/notification.py
aldryn_forms/contrib/email_notifications/migrations/0001_initial.py
aldryn_forms/contrib/email_notifications/migrations/0002_form_plugin_add_missing_permission.py
aldryn_forms/contrib/email_notifications/migrations/0003_auto_20180206_1733.py
aldryn_forms/contrib/email_notifications/migrations/0004_auto_20190104_1242.py
aldryn_forms/contrib/email_notifications/migrations/0005_add_field_reply_to_email.py
aldryn_forms/contrib/email_notifications/migrations/__init__.py
aldryn_forms/contrib/email_notifications/static/email_notifications/admin/email-notifications.css
aldryn_forms/locale/de/LC_MESSAGES/django.mo
aldryn_forms/locale/de/LC_MESSAGES/django.po
aldryn_forms/locale/en/LC_MESSAGES/django.mo
aldryn_forms/locale/en/LC_MESSAGES/django.po
aldryn_forms/locale/fa/LC_MESSAGES/django.mo
aldryn_forms/locale/fa/LC_MESSAGES/django.po
aldryn_forms/locale/fr/LC_MESSAGES/django.mo
aldryn_forms/locale/fr/LC_MESSAGES/django.po
aldryn_forms/locale/it/LC_MESSAGES/django.mo
aldryn_forms/locale/it/LC_MESSAGES/django.po
aldryn_forms/locale/lt/LC_MESSAGES/django.mo
aldryn_forms/locale/lt/LC_MESSAGES/django.po
aldryn_forms/locale/nl/LC_MESSAGES/django.mo
aldryn_forms/locale/nl/LC_MESSAGES/django.po
aldryn_forms-6.2.1.dist-info/LICENSE.txt
aldryn_forms-6.2.1.dist-info/METADATA
aldryn_forms-6.2.1.dist-info/WHEEL
aldryn_forms-6.2.1.dist-info/top_level.txt
aldryn_forms-6.2.1.dist-info/RECORD
