Metadata-Version: 2.1
Name: aldryn-forms
Version: 6.2.1
Summary: Create forms and embed them on CMS pages
Home-page: https://github.com/aldryn/aldryn-forms
Author: Divio AG
Author-email: info@divio.ch
License: BSD
Platform: UNKNOWN
Classifier: Development Status :: 5 - Production/Stable
Classifier: Environment :: Web Environment
Classifier: Intended Audience :: Developers
Classifier: License :: OSI Approved :: BSD License
Classifier: Operating System :: OS Independent
Classifier: Framework :: Django
Classifier: Framework :: Django :: 2.2
Classifier: Programming Language :: Python
Classifier: Programming Language :: Python :: 3
Classifier: Programming Language :: Python :: 3.4
Classifier: Programming Language :: Python :: 3.5
Classifier: Programming Language :: Python :: 3.6
Classifier: Topic :: Internet :: WWW/HTTP
Classifier: Topic :: Internet :: WWW/HTTP :: Dynamic Content
Classifier: Topic :: Software Development
Classifier: Topic :: Software Development :: Libraries
Requires-Dist: django (>=2.0)
Requires-Dist: aldryn-boilerplates (>=0.7.5)
Requires-Dist: django-cms (>=3.5)
Requires-Dist: django-emailit
Requires-Dist: djangocms-text-ckeditor
Requires-Dist: djangocms-attributes-field (>=1.0.0)
Requires-Dist: django-tablib
Requires-Dist: tablib
Requires-Dist: pillow
Requires-Dist: django-filer
Requires-Dist: django-sizefield
Requires-Dist: six (>=1.0)
Provides-Extra: captcha
Requires-Dist: django-simple-captcha ; extra == 'captcha'
